gist/__init__.py
gist/client.py
gist/gist.py
gist/version.py
python_gist-0.10.6.dist-info/entry_points.txt
python_gist-0.10.6.dist-info/LICENSE
python_gist-0.10.6.dist-info/WHEEL
python_gist-0.10.6.dist-info/METADATA
python_gist-0.10.6.dist-info/RECORD
