Metadata-Version: 2.1
Name: python-gist
Version: 0.10.6
Summary: Manage github gists
Home-page: https://github.com/jdowner/gist
License: MIT
Keywords: gist,github,git
Author: Joshua Downer
Author-email: joshua.downer@gmail.com
Requires-Python: >=3.6,<4.0
Classifier: Development Status :: 5 - Production/Stable
Classifier: Environment :: Console
Classifier: Intended Audience :: Developers
Classifier: Intended Audience :: End Users/Desktop
Classifier: Intended Audience :: System Administrators
Classifier: License :: OSI Approved :: MIT License
Classifier: Operating System :: Unix
Classifier: Programming Language :: Python
Classifier: Programming Language :: Python :: 3
Classifier: Programming Language :: Python :: 3.6
Classifier: Programming Language :: Python :: 3.7
Classifier: Programming Language :: Python :: 3.8
Classifier: Programming Language :: Python :: 3.9
Classifier: Topic :: Software Development
Classifier: Topic :: Software Development :: Version Control
Classifier: Topic :: Utilities
Requires-Dist: python-gnupg (>=0.4.7,<0.5.0)
Requires-Dist: requests (>=2.25.1,<3.0.0)
Project-URL: Documentation, https://github.com/jdowner/gist
Project-URL: Repository, https://github.com/jdowner/gist
